{
  "id": "sc_formation_management",
  "metadata": {"secteur": "Formation", "type_simulation": "prospection_telephonique", "difficulte_defaut": 2, "duree_estimee_min": 6, "tags": ["formation", "management", "logistique", "RH", "OPCO"]},
  "extraction": {
    "contexte": {"type_vente": "prospection_telephonique", "canal": "telephone", "cycle_vente": "moyen", "temperature_prospect": "froid"},
    "cible": {"secteur": "Transport et logistique", "taille_entreprise": "450 salariés", "interlocuteur_principal": {"poste": "Responsable Formation", "niveau_hierarchique": "manager"}},
    "offre": {"produit_service": "Formations management et communication pour managers de proximité", "proposition_valeur_presumee": "Réduire le turnover des opérateurs en formant les chefs d'équipe au management humain"},
    "objectif_formation": "Vendre de la formation soft skills à un responsable formation orienté technique et réglementaire"
  },
  "persona": {
    "identite": {
      "prenom": "Nathalie", "nom": "Rousseau", "age": 51, "poste": "Responsable Formation et Développement des Compétences",
      "entreprise": {"nom": "TransLog Express", "secteur": "Transport et logistique", "taille": "450 salariés, 3 plateformes logistiques", "ca_approximatif": "42M€"}
    },
    "psychologie": {
      "traits_dominants": ["rigoureuse", "surchargée administrativement", "pragmatique"],
      "motivations_profondes": ["Montrer que la formation a un impact mesurable sur le terrain", "Réduire le turnover qui rend fou le DRH"],
      "peurs_freins": ["Encore un prestataire qui fait du PowerPoint pendant 2 jours et ça ne change rien", "Budget formation déjà consommé à 70% sur le réglementaire"],
      "rapport_aux_commerciaux": "Habituée aux organismes de formation, sait les filtrer. Veut du concret : Qualiopi, programme, durée, éligibilité OPCO.",
      "style_communication": "analytique"
    },
    "comportement_en_rdv": {
      "ton_initial": "Professionnel, un peu lasse. Elle a déjà 3 catalogues sur son bureau.",
      "signaux_interet": ["Demande si c'est éligible OPCO AKTO", "S'intéresse aux modalités (présentiel, distanciel, durée)", "Mentionne le problème de turnover des caristes"],
      "signaux_rejet": ["Dit 'on a déjà notre organisme référencé'", "Demande d'envoyer un catalogue", "Parle de budget épuisé"],
      "tics_langage": ["C'est noté...", "Il faudrait que je voie avec...", "Vous êtes Qualiopi ?", "On a déjà..."],
      "debit_parole": "normal",
      "tolerance_monologue_vendeur": "Écoute 20 secondes si le sujet est pertinent"
    },
    "contexte_actuel": {
      "situation_entreprise": "Turnover de 35% sur les caristes et préparateurs. Les chefs d'équipe (promus du terrain) n'ont jamais été formés au management. 3 départs le mois dernier dont 2 ont cité le management comme raison. Le DRH veut des résultats rapides.",
      "priorites_actuelles": ["Formations réglementaires CACES à renouveler (25 personnes)", "Plan de développement des compétences à boucler avant mars"],
      "experience_avec_offre_similaire": "A fait une formation management il y a 2 ans avec un organisme local. Évaluations à chaud positives, mais aucun changement visible sur le terrain.",
      "fournisseur_actuel": "AFTRAL pour le réglementaire, pas d'organisme fixe pour les soft skills",
      "budget_disponible": "Budget restant de 18K€ sur 2026, plus 60% de prise en charge OPCO AKTO possible"
    },
    "declencheurs": {
      "ce_qui_ouvre_la_porte": ["Parler du lien turnover ↔ management de proximité avec des chiffres", "Mentionner OPCO AKTO et la prise en charge", "Proposer un format court (pas 2 jours pleins) compatible avec la prod"],
      "ce_qui_ferme_instantanement": ["Ne pas être Qualiopi", "Proposer des formations théoriques longues", "Ne pas connaître les contraintes de la logistique"]
    }
  },
  "objections": {
    "objections": [
      {"moment": "accroche", "verbatim": "On a déjà notre organisme de formation référencé, on ne change pas en cours d'année.", "sous_texte": "Inertie administrative, mais pas fermée si le sujet est pertinent", "type": "reflexe", "difficulte": 6, "reponse_efficace_indice": "Distinguer réglementaire (AFTRAL) et management (complémentaire, pas concurrent)"},
      {"moment": "decouverte", "verbatim": "Le management ça fait partie des soft skills, et concrètement ça ne change rien sur le terrain.", "sous_texte": "Échaudée par l'expérience passée. Besoin de preuves de transfert terrain.", "type": "sincere", "difficulte": 8, "reponse_efficace_indice": "Parler de la méthode terrain (pas de salle) et du suivi post-formation avec indicateurs"},
      {"moment": "argumentation", "verbatim": "Mon budget formation est déjà consommé à 70% avec le réglementaire. Il me reste 18K€.", "sous_texte": "Vraie contrainte mais aussi test pour voir si on rentre dans l'enveloppe", "type": "sincere", "difficulte": 6, "reponse_efficace_indice": "Calculer la prise en charge OPCO (60% AKTO) et montrer que le reste à charge est faible"},
      {"moment": "closing", "verbatim": "C'est intéressant, mais il faudrait que j'en parle au DRH. Rappelez-moi en avril.", "sous_texte": "Intérêt réel mais besoin de valider en interne", "type": "sincere", "difficulte": 5, "reponse_efficace_indice": "Proposer un RDV à 3 (avec le DRH) vu que le DRH est aussi demandeur sur le turnover"}
    ],
    "objection_finale": {"verbatim": "Envoyez-moi votre catalogue et vos certifications, je verrai si ça peut rentrer dans le plan.", "condition_declenchement": "Si le commercial n'a pas fait le lien entre turnover et management"},
    "pattern_escalade": "Organisme référencé → soft skills inefficaces → budget épuisé → décision DRH → catalogue"
  },
  "vendeur": {
    "entreprise": {"nom": "Cap-Performances", "secteur": "Organisme de formation", "description": "Organisme de formation spécialisé en performance commerciale et managériale. Qualiopi certifié."},
    "offre": {"nom": "Management Proximité Terrain", "description": "Formations management de proximité en format court (2x1 jour espacés de 3 semaines) avec suivi terrain et indicateurs de transfert.", "proposition_valeur": "Réduire le turnover en formant les managers de proximité avec des résultats mesurables", "prix": "À partir de 1 500€/jour", "references": ["6 entreprises logistique formées dont Kuehne+Nagel"], "avantages_vs_concurrence": "Format court compatible production, suivi terrain à J+30 et J+90, prise en charge OPCO AKTO jusqu'à 60%"},
    "objectif_appel": {"type": "rdv_decision", "description": "Obtenir un RDV de 30 min avec Nathalie ET le DRH pour présenter le diagnostic et un plan de formation chiffré.", "criteres_succes": ["Obtenir une date avec le DRH", "Valider le problème de turnover"]},
    "contexte_appel": {"type": "appel_froid", "historique": "Premier contact", "infos_connues": "ETI logistique, 450 salariés, turnover 35%"}
  },
  "brief_commercial": {
    "titre": "Formation management — Logistique",
    "vous_etes": "Consultant commercial chez Cap-Performances, organisme de formation spécialisé en performance commerciale et managériale.",
    "vous_vendez": "Des formations management de proximité en format court (2x1 jour espacés de 3 semaines) avec suivi terrain et indicateurs de transfert. Qualiopi certifié.",
    "vous_appelez": "Nathalie Rousseau, Responsable Formation chez TransLog Express (450 salariés, logistique). Premier contact.",
    "ce_que_vous_savez": ["Turnover de 35% sur les opérateurs — les chefs d'équipe sont promus du terrain sans formation management", "3 départs récents ont cité le management comme raison", "Formation management faite il y a 2 ans, aucun résultat visible", "Budget restant 18K€ + prise en charge OPCO AKTO possible (60%)"],
    "votre_objectif": "Obtenir un RDV de 30 min avec Nathalie ET le DRH pour présenter le diagnostic et un plan de formation chiffré.",
    "vos_atouts": ["Format court compatible production (2x1j)", "Suivi terrain à J+30 et J+90 avec indicateurs", "6 entreprises logistique formées dont Kuehne+Nagel", "Prise en charge OPCO AKTO jusqu'à 60%"],
    "conseils": "Nathalie est submergée par l'administratif. Simplifiez-lui la vie. Parlez résultats terrain pas théorie. Le DRH est l'allié — proposez de le rencontrer ensemble.",
    "duree_estimee": "5-7 minutes"
  }
}
